jwt_pydantic/__init__.py
jwt_pydantic/main.py
jwt_pydantic/middleware.py
jwt_pydantic-0.0.7.dist-info/LICENSE
jwt_pydantic-0.0.7.dist-info/METADATA
jwt_pydantic-0.0.7.dist-info/WHEEL
jwt_pydantic-0.0.7.dist-info/top_level.txt
jwt_pydantic-0.0.7.dist-info/RECORD
