Metadata-Version: 2.1
Name: jwt-pydantic
Version: 0.0.7
Summary: Verify JWT claims using the powerful features of Pydantic.
Author: Adam Powis
License: The MIT License (MIT)
Classifier: License :: OSI Approved :: MIT License
Requires-Python: >=3.8.0
License-File: LICENSE
Requires-Dist: httpx
Requires-Dist: fastapi
Requires-Dist: pydantic
Requires-Dist: python-jose
Provides-Extra: test
Requires-Dist: black ; extra == 'test'
Requires-Dist: mypy ; extra == 'test'
Requires-Dist: pytest ; extra == 'test'
Requires-Dist: pytest-cov ; extra == 'test'
Requires-Dist: pylint ; extra == 'test'
Requires-Dist: types-python-jose (==3.3.4) ; extra == 'test'
